{
  "project_info": {
    "project_number": "28958942252",
    "project_id": "speak-d3a4f",
    "storage_bucket": "speak-d3a4f.appspot.com"
  },
  "client": [
    {
      "client_info": {
        "mobilesdk_app_id": "1:28958942252:android:0fbe2b0e68006cc1289d89",
        "android_client_info": {
          "package_name": "com.mycompany.speak6"
        }
      },
      "oauth_client": [
        {
          "client_id": "28958942252-h5qfnd93hh4qb5fklncv8pr0d1tidho6.apps.googleusercontent.com",
          "client_type": 1,
          "android_info": {
            "package_name": "com.mycompany.speak6",
            "certificate_hash": "9bbb3186b2189ef16d8f272bdab59362c395cbb4"
          }
        },
        {
          "client_id": "28958942252-58mm3ph8bctg6obm3770lcmv5e650g9f.apps.googleusercontent.com",
          "client_type": 3
        }
      ],
      "api_key": [
        {
          "current_key": "AIzaSyC6hOzMwrM27svhJbLWVSze7tiyrBYHeaU"
        }
      ],
      "services": {
        "appinvite_service": {
          "other_platform_oauth_client": [
            {
              "client_id": "28958942252-58mm3ph8bctg6obm3770lcmv5e650g9f.apps.googleusercontent.com",
              "client_type": 3
            },
            {
              "client_id": "28958942252-c1ck6hhrcbkfpcds93m9640n68fks73o.apps.googleusercontent.com",
              "client_type": 2,
              "ios_info": {
                "bundle_id": "com.mycompany.speak6"
              }
            }
          ]
        }
      }
    }
  ],
  "configuration_version": "1"
}